antenna.libs/libcrypto-c19c2cf8.so.3
antenna.libs/libssl-63597a81.so.3
antenna/__init__.py
antenna/_antenna.cpython-313-x86_64-linux-gnu.so
antenna_stt-0.4.0.dist-info/METADATA
antenna_stt-0.4.0.dist-info/WHEEL
antenna_stt-0.4.0.dist-info/licenses/LICENSE
antenna_stt-0.4.0.dist-info/RECORD
