Metadata-Version: 2.4
Name: antenna-stt
Version: 0.4.0
Classifier: Development Status :: 4 - Beta
Classifier: Intended Audience :: Developers
Classifier: License :: OSI Approved :: MIT License
Classifier: Programming Language :: Python :: 3
Classifier: Programming Language :: Python :: 3.8
Classifier: Programming Language :: Python :: 3.9
Classifier: Programming Language :: Python :: 3.10
Classifier: Programming Language :: Python :: 3.11
Classifier: Programming Language :: Python :: 3.12
Classifier: Programming Language :: Rust
Classifier: Topic :: Multimedia :: Sound/Audio :: Speech
Requires-Dist: numpy>=1.20
License-File: LICENSE
Summary: Rust-powered Speech-to-Text toolkit with Whisper, Distil-Whisper, and streaming transcription
Keywords: speech-to-text,whisper,audio,transcription,rust,asr,stt
Author-email: Fiction AI Studios <hello@fiction.ai>
Maintainer-email: Fiction AI Studios <hello@fiction.ai>
License: MIT
Requires-Python: >=3.8
Project-URL: Homepage, https://github.com/fiction-ai-studios/antenna
Project-URL: Documentation, https://github.com/fiction-ai-studios/antenna#readme
Project-URL: Repository, https://github.com/fiction-ai-studios/antenna
Project-URL: Issues, https://github.com/fiction-ai-studios/antenna/issues
Project-URL: Changelog, https://github.com/fiction-ai-studios/antenna/releases
